[{"name":"protected CodeLines jsOutput()","description":"io.spine.js.generate.JsCodeGenerator.jsOutput","location":"proto-js-plugin/io.spine.js.generate/-js-code-generator/js-output.html","searchKeys":["jsOutput","protected CodeLines jsOutput()","io.spine.js.generate.JsCodeGenerator.jsOutput"]},{"name":"protected DefaultProject defaultProject(Project project)","description":"io.spine.js.gradle.Extension.defaultProject","location":"proto-js-plugin/io.spine.js.gradle/-extension/default-project.html","searchKeys":["defaultProject","protected DefaultProject defaultProject(Project project)","io.spine.js.gradle.Extension.defaultProject"]},{"name":"protected Directory generatedRoot()","description":"io.spine.js.generate.GenerationTask.generatedRoot","location":"proto-js-plugin/io.spine.js.generate/-generation-task/generated-root.html","searchKeys":["generatedRoot","protected Directory generatedRoot()","io.spine.js.generate.GenerationTask.generatedRoot"]},{"name":"protected FileSet filter(FileSet fileSet)","description":"io.spine.js.generate.GenerationTask.filter","location":"proto-js-plugin/io.spine.js.generate/-generation-task/filter.html","searchKeys":["filter","protected FileSet filter(FileSet fileSet)","io.spine.js.generate.GenerationTask.filter"]},{"name":"protected File getMainDescriptorSet(Project project)","description":"io.spine.js.gradle.JsProtocConfigurationPlugin.getMainDescriptorSet","location":"proto-js-plugin/io.spine.js.gradle/-js-protoc-configuration-plugin/get-main-descriptor-set.html","searchKeys":["getMainDescriptorSet","protected File getMainDescriptorSet(Project project)","io.spine.js.gradle.JsProtocConfigurationPlugin.getMainDescriptorSet"]},{"name":"protected File getTestDescriptorSet(Project project)","description":"io.spine.js.gradle.JsProtocConfigurationPlugin.getTestDescriptorSet","location":"proto-js-plugin/io.spine.js.gradle/-js-protoc-configuration-plugin/get-test-descriptor-set.html","searchKeys":["getTestDescriptorSet","protected File getTestDescriptorSet(Project project)","io.spine.js.gradle.JsProtocConfigurationPlugin.getTestDescriptorSet"]},{"name":"protected Path generatedFilesBaseDir(Project project)","description":"io.spine.js.gradle.JsProtocConfigurationPlugin.generatedFilesBaseDir","location":"proto-js-plugin/io.spine.js.gradle/-js-protoc-configuration-plugin/generated-files-base-dir.html","searchKeys":["generatedFilesBaseDir","protected Path generatedFilesBaseDir(Project project)","io.spine.js.gradle.JsProtocConfigurationPlugin.generatedFilesBaseDir"]},{"name":"protected Supplier<File> mainDescriptorFile(Project project)","description":"io.spine.js.gradle.ProtoJsPlugin.mainDescriptorFile","location":"proto-js-plugin/io.spine.js.gradle/-proto-js-plugin/main-descriptor-file.html","searchKeys":["mainDescriptorFile","protected Supplier<File> mainDescriptorFile(Project project)","io.spine.js.gradle.ProtoJsPlugin.mainDescriptorFile"]},{"name":"protected Supplier<File> testDescriptorFile(Project project)","description":"io.spine.js.gradle.ProtoJsPlugin.testDescriptorFile","location":"proto-js-plugin/io.spine.js.gradle/-proto-js-plugin/test-descriptor-file.html","searchKeys":["testDescriptorFile","protected Supplier<File> testDescriptorFile(Project project)","io.spine.js.gradle.ProtoJsPlugin.testDescriptorFile"]},{"name":"protected abstract void generateFor(FileSet fileSet)","description":"io.spine.js.generate.GenerationTask.generateFor","location":"proto-js-plugin/io.spine.js.generate/-generation-task/generate-for.html","searchKeys":["generateFor","protected abstract void generateFor(FileSet fileSet)","io.spine.js.generate.GenerationTask.generateFor"]},{"name":"protected void GenerationTask(Directory generatedRoot)","description":"io.spine.js.generate.GenerationTask.GenerationTask","location":"proto-js-plugin/io.spine.js.generate/-generation-task/-generation-task.html","searchKeys":["GenerationTask","protected void GenerationTask(Directory generatedRoot)","io.spine.js.generate.GenerationTask.GenerationTask"]},{"name":"protected void JsCodeGenerator(CodeLines jsOutput)","description":"io.spine.js.generate.JsCodeGenerator.JsCodeGenerator","location":"proto-js-plugin/io.spine.js.generate/-js-code-generator/-js-code-generator.html","searchKeys":["JsCodeGenerator","protected void JsCodeGenerator(CodeLines jsOutput)","io.spine.js.generate.JsCodeGenerator.JsCodeGenerator"]},{"name":"protected void configureProtocPlugins(NamedDomainObjectContainer<ExecutableLocator> plugins, Project project)","description":"io.spine.js.gradle.JsProtocConfigurationPlugin.configureProtocPlugins","location":"proto-js-plugin/io.spine.js.gradle/-js-protoc-configuration-plugin/configure-protoc-plugins.html","searchKeys":["configureProtocPlugins","protected void configureProtocPlugins(NamedDomainObjectContainer<ExecutableLocator> plugins, Project project)","io.spine.js.gradle.JsProtocConfigurationPlugin.configureProtocPlugins"]},{"name":"protected void generateFor(FileSet fileSet)","description":"io.spine.js.generate.AppendTypeUrlGetter.generateFor","location":"proto-js-plugin/io.spine.js.generate/-append-type-url-getter/generate-for.html","searchKeys":["generateFor","protected void generateFor(FileSet fileSet)","io.spine.js.generate.AppendTypeUrlGetter.generateFor"]},{"name":"protected void generateFor(FileSet fileSet)","description":"io.spine.js.generate.imports.ResolveImports.generateFor","location":"proto-js-plugin/io.spine.js.generate.imports/-resolve-imports/generate-for.html","searchKeys":["generateFor","protected void generateFor(FileSet fileSet)","io.spine.js.generate.imports.ResolveImports.generateFor"]},{"name":"protected void generateFor(FileSet fileSet)","description":"io.spine.js.generate.index.GenerateIndexFile.generateFor","location":"proto-js-plugin/io.spine.js.generate.index/-generate-index-file/generate-for.html","searchKeys":["generateFor","protected void generateFor(FileSet fileSet)","io.spine.js.generate.index.GenerateIndexFile.generateFor"]},{"name":"protected void generateFor(FileSet fileSet)","description":"io.spine.js.generate.parse.GenerateKnownTypeParsers.generateFor","location":"proto-js-plugin/io.spine.js.generate.parse/-generate-known-type-parsers/generate-for.html","searchKeys":["generateFor","protected void generateFor(FileSet fileSet)","io.spine.js.generate.parse.GenerateKnownTypeParsers.generateFor"]},{"name":"public CodeLines value()","description":"io.spine.js.generate.output.snippet.MapExportSnippet.value","location":"proto-js-plugin/io.spine.js.generate.output.snippet/-map-export-snippet/value.html","searchKeys":["value","public CodeLines value()","io.spine.js.generate.output.snippet.MapExportSnippet.value"]},{"name":"public CodeLines value()","description":"io.spine.js.generate.output.snippet.Method.value","location":"proto-js-plugin/io.spine.js.generate.output.snippet/-method/value.html","searchKeys":["value","public CodeLines value()","io.spine.js.generate.output.snippet.Method.value"]},{"name":"public CodeLines value()","description":"io.spine.js.generate.parse.GeneratedParser.value","location":"proto-js-plugin/io.spine.js.generate.parse/-generated-parser/value.html","searchKeys":["value","public CodeLines value()","io.spine.js.generate.parse.GeneratedParser.value"]},{"name":"public FieldDescriptor descriptor()","description":"io.spine.js.generate.field.FieldToParse.descriptor","location":"proto-js-plugin/io.spine.js.generate.field/-field-to-parse/descriptor.html","searchKeys":["descriptor","public FieldDescriptor descriptor()","io.spine.js.generate.field.FieldToParse.descriptor"]},{"name":"public FileReference path()","description":"io.spine.js.generate.imports.ImportStatement.path","location":"proto-js-plugin/io.spine.js.generate.imports/-import-statement/path.html","searchKeys":["path","public FileReference path()","io.spine.js.generate.imports.ImportStatement.path"]},{"name":"public ImportStatement replacePath(CharSequence newPath)","description":"io.spine.js.generate.imports.ImportStatement.replacePath","location":"proto-js-plugin/io.spine.js.generate.imports/-import-statement/replace-path.html","searchKeys":["replacePath","public ImportStatement replacePath(CharSequence newPath)","io.spine.js.generate.imports.ImportStatement.replacePath"]},{"name":"public Import toDefault()","description":"io.spine.js.generate.output.snippet.Import.toDefault","location":"proto-js-plugin/io.spine.js.generate.output.snippet/-import/to-default.html","searchKeys":["toDefault","public Import toDefault()","io.spine.js.generate.output.snippet.Import.toDefault"]},{"name":"public MapExportSnippet.Builder withEntries<T>(List<Map.Entry<String, T>> entriesToAdd)","description":"io.spine.js.generate.output.snippet.MapExportSnippet.Builder.withEntries","location":"proto-js-plugin/io.spine.js.generate.output.snippet/-map-export-snippet/-builder/with-entries.html","searchKeys":["withEntries","public MapExportSnippet.Builder withEntries<T>(List<Map.Entry<String, T>> entriesToAdd)","io.spine.js.generate.output.snippet.MapExportSnippet.Builder.withEntries"]},{"name":"public MapExportSnippet.Builder withEntry(String key, Object value)","description":"io.spine.js.generate.output.snippet.MapExportSnippet.Builder.withEntry","location":"proto-js-plugin/io.spine.js.generate.output.snippet/-map-export-snippet/-builder/with-entry.html","searchKeys":["withEntry","public MapExportSnippet.Builder withEntry(String key, Object value)","io.spine.js.generate.output.snippet.MapExportSnippet.Builder.withEntry"]},{"name":"public MapExportSnippet build()","description":"io.spine.js.generate.output.snippet.MapExportSnippet.Builder.build","location":"proto-js-plugin/io.spine.js.generate.output.snippet/-map-export-snippet/-builder/build.html","searchKeys":["build","public MapExportSnippet build()","io.spine.js.generate.output.snippet.MapExportSnippet.Builder.build"]},{"name":"public Method.Builder appendToBody(CodeLine line)","description":"io.spine.js.generate.output.snippet.Method.Builder.appendToBody","location":"proto-js-plugin/io.spine.js.generate.output.snippet/-method/-builder/append-to-body.html","searchKeys":["appendToBody","public Method.Builder appendToBody(CodeLine line)","io.spine.js.generate.output.snippet.Method.Builder.appendToBody"]},{"name":"public Method.Builder appendToBody(String line)","description":"io.spine.js.generate.output.snippet.Method.Builder.appendToBody","location":"proto-js-plugin/io.spine.js.generate.output.snippet/-method/-builder/append-to-body.html","searchKeys":["appendToBody","public Method.Builder appendToBody(String line)","io.spine.js.generate.output.snippet.Method.Builder.appendToBody"]},{"name":"public Method.Builder withParameters(Array<String> parameters)","description":"io.spine.js.generate.output.snippet.Method.Builder.withParameters","location":"proto-js-plugin/io.spine.js.generate.output.snippet/-method/-builder/with-parameters.html","searchKeys":["withParameters","public Method.Builder withParameters(Array<String> parameters)","io.spine.js.generate.output.snippet.Method.Builder.withParameters"]},{"name":"public Method build()","description":"io.spine.js.generate.output.snippet.Method.Builder.build","location":"proto-js-plugin/io.spine.js.generate.output.snippet/-method/-builder/build.html","searchKeys":["build","public Method build()","io.spine.js.generate.output.snippet.Method.Builder.build"]},{"name":"public Path importedFilePath()","description":"io.spine.js.generate.imports.ImportStatement.importedFilePath","location":"proto-js-plugin/io.spine.js.generate.imports/-import-statement/imported-file-path.html","searchKeys":["importedFilePath","public Path importedFilePath()","io.spine.js.generate.imports.ImportStatement.importedFilePath"]},{"name":"public Path sourceDirectory()","description":"io.spine.js.generate.imports.ImportStatement.sourceDirectory","location":"proto-js-plugin/io.spine.js.generate.imports/-import-statement/source-directory.html","searchKeys":["sourceDirectory","public Path sourceDirectory()","io.spine.js.generate.imports.ImportStatement.sourceDirectory"]},{"name":"public String content()","description":"io.spine.js.generate.output.snippet.Comment.content","location":"proto-js-plugin/io.spine.js.generate.output.snippet/-comment/content.html","searchKeys":["content","public String content()","io.spine.js.generate.output.snippet.Comment.content"]},{"name":"public String content()","description":"io.spine.js.generate.output.snippet.Import.content","location":"proto-js-plugin/io.spine.js.generate.output.snippet/-import/content.html","searchKeys":["content","public String content()","io.spine.js.generate.output.snippet.Import.content"]},{"name":"public String content()","description":"io.spine.js.generate.output.snippet.Return.content","location":"proto-js-plugin/io.spine.js.generate.output.snippet/-return/content.html","searchKeys":["content","public String content()","io.spine.js.generate.output.snippet.Return.content"]},{"name":"public String content()","description":"io.spine.js.generate.output.snippet.VariableDeclaration.content","location":"proto-js-plugin/io.spine.js.generate.output.snippet/-variable-declaration/content.html","searchKeys":["content","public String content()","io.spine.js.generate.output.snippet.VariableDeclaration.content"]},{"name":"public String messageVariable()","description":"io.spine.js.generate.field.FieldToParse.messageVariable","location":"proto-js-plugin/io.spine.js.generate.field/-field-to-parse/message-variable.html","searchKeys":["messageVariable","public String messageVariable()","io.spine.js.generate.field.FieldToParse.messageVariable"]},{"name":"public String namedAs(String importName)","description":"io.spine.js.generate.output.snippet.Import.namedAs","location":"proto-js-plugin/io.spine.js.generate.output.snippet/-import/named-as.html","searchKeys":["namedAs","public String namedAs(String importName)","io.spine.js.generate.output.snippet.Import.namedAs"]},{"name":"public String toString()","description":"io.spine.js.generate.output.CodeLine.toString","location":"proto-js-plugin/io.spine.js.generate.output/-code-line/to-string.html","searchKeys":["toString","public String toString()","io.spine.js.generate.output.CodeLine.toString"]},{"name":"public String toString()","description":"io.spine.js.generate.output.CodeLines.toString","location":"proto-js-plugin/io.spine.js.generate.output/-code-lines/to-string.html","searchKeys":["toString","public String toString()","io.spine.js.generate.output.CodeLines.toString"]},{"name":"public String value()","description":"io.spine.js.generate.field.FieldToParse.value","location":"proto-js-plugin/io.spine.js.generate.field/-field-to-parse/value.html","searchKeys":["value","public String value()","io.spine.js.generate.field.FieldToParse.value"]},{"name":"public Task generateParsersTask()","description":"io.spine.js.gradle.Extension.generateParsersTask","location":"proto-js-plugin/io.spine.js.gradle/-extension/generate-parsers-task.html","searchKeys":["generateParsersTask","public Task generateParsersTask()","io.spine.js.gradle.Extension.generateParsersTask"]},{"name":"public abstract B setJsOutput(CodeLines jsOutput)","description":"io.spine.js.generate.field.parser.primitive.PrimitiveParser.Builder.setJsOutput","location":"proto-js-plugin/io.spine.js.generate.field.parser.primitive/-primitive-parser/-builder/set-js-output.html","searchKeys":["setJsOutput","public abstract B setJsOutput(CodeLines jsOutput)","io.spine.js.generate.field.parser.primitive.PrimitiveParser.Builder.setJsOutput"]},{"name":"public abstract CodeLines value()","description":"io.spine.js.generate.Snippet.value","location":"proto-js-plugin/io.spine.js.generate/-snippet/value.html","searchKeys":["value","public abstract CodeLines value()","io.spine.js.generate.Snippet.value"]},{"name":"public abstract PrimitiveParser build()","description":"io.spine.js.generate.field.parser.primitive.PrimitiveParser.Builder.build","location":"proto-js-plugin/io.spine.js.generate.field.parser.primitive/-primitive-parser/-builder/build.html","searchKeys":["build","public abstract PrimitiveParser build()","io.spine.js.generate.field.parser.primitive.PrimitiveParser.Builder.build"]},{"name":"public abstract String content()","description":"io.spine.js.generate.output.CodeLine.content","location":"proto-js-plugin/io.spine.js.generate.output/-code-line/content.html","searchKeys":["content","public abstract String content()","io.spine.js.generate.output.CodeLine.content"]},{"name":"public abstract class CodeLine","description":"io.spine.js.generate.output.CodeLine","location":"proto-js-plugin/io.spine.js.generate.output/-code-line/index.html","searchKeys":["CodeLine","public abstract class CodeLine","io.spine.js.generate.output.CodeLine"]},{"name":"public abstract class FieldGenerator extends JsCodeGenerator","description":"io.spine.js.generate.field.FieldGenerator","location":"proto-js-plugin/io.spine.js.generate.field/-field-generator/index.html","searchKeys":["FieldGenerator","public abstract class FieldGenerator extends JsCodeGenerator","io.spine.js.generate.field.FieldGenerator"]},{"name":"public abstract class GenerationTask","description":"io.spine.js.generate.GenerationTask","location":"proto-js-plugin/io.spine.js.generate/-generation-task/index.html","searchKeys":["GenerationTask","public abstract class GenerationTask","io.spine.js.generate.GenerationTask"]},{"name":"public abstract class JsCodeGenerator","description":"io.spine.js.generate.JsCodeGenerator","location":"proto-js-plugin/io.spine.js.generate/-js-code-generator/index.html","searchKeys":["JsCodeGenerator","public abstract class JsCodeGenerator","io.spine.js.generate.JsCodeGenerator"]},{"name":"public abstract void exitNullCheck()","description":"io.spine.js.generate.field.precondition.FieldPrecondition.exitNullCheck","location":"proto-js-plugin/io.spine.js.generate.field.precondition/-field-precondition/exit-null-check.html","searchKeys":["exitNullCheck","public abstract void exitNullCheck()","io.spine.js.generate.field.precondition.FieldPrecondition.exitNullCheck"]},{"name":"public abstract void generate()","description":"io.spine.js.generate.JsCodeGenerator.generate","location":"proto-js-plugin/io.spine.js.generate/-js-code-generator/generate.html","searchKeys":["generate","public abstract void generate()","io.spine.js.generate.JsCodeGenerator.generate"]},{"name":"public abstract void parseIntoVariable(String value, String variable)","description":"io.spine.js.generate.field.parser.FieldParser.parseIntoVariable","location":"proto-js-plugin/io.spine.js.generate.field.parser/-field-parser/parse-into-variable.html","searchKeys":["parseIntoVariable","public abstract void parseIntoVariable(String value, String variable)","io.spine.js.generate.field.parser.FieldParser.parseIntoVariable"]},{"name":"public abstract void parseIntoVariable(String value, String variable)","description":"io.spine.js.generate.field.parser.primitive.PrimitiveParser.parseIntoVariable","location":"proto-js-plugin/io.spine.js.generate.field.parser.primitive/-primitive-parser/parse-into-variable.html","searchKeys":["parseIntoVariable","public abstract void parseIntoVariable(String value, String variable)","io.spine.js.generate.field.parser.primitive.PrimitiveParser.parseIntoVariable"]},{"name":"public abstract void performNullCheck(String value, String mergeFieldFormat)","description":"io.spine.js.generate.field.precondition.FieldPrecondition.performNullCheck","location":"proto-js-plugin/io.spine.js.generate.field.precondition/-field-precondition/perform-null-check.html","searchKeys":["performNullCheck","public abstract void performNullCheck(String value, String mergeFieldFormat)","io.spine.js.generate.field.precondition.FieldPrecondition.performNullCheck"]},{"name":"public boolean equals(Object o)","description":"io.spine.js.generate.output.CodeLine.equals","location":"proto-js-plugin/io.spine.js.generate.output/-code-line/equals.html","searchKeys":["equals","public boolean equals(Object o)","io.spine.js.generate.output.CodeLine.equals"]},{"name":"public boolean equals(Object o)","description":"io.spine.js.generate.output.CodeLines.equals","location":"proto-js-plugin/io.spine.js.generate.output/-code-lines/equals.html","searchKeys":["equals","public boolean equals(Object o)","io.spine.js.generate.output.CodeLines.equals"]},{"name":"public boolean importedFileExists()","description":"io.spine.js.generate.imports.ImportStatement.importedFileExists","location":"proto-js-plugin/io.spine.js.generate.imports/-import-statement/imported-file-exists.html","searchKeys":["importedFileExists","public boolean importedFileExists()","io.spine.js.generate.imports.ImportStatement.importedFileExists"]},{"name":"public class AppendTypeUrlGetter extends GenerationTask","description":"io.spine.js.generate.AppendTypeUrlGetter","location":"proto-js-plugin/io.spine.js.generate/-append-type-url-getter/index.html","searchKeys":["AppendTypeUrlGetter","public class AppendTypeUrlGetter extends GenerationTask","io.spine.js.generate.AppendTypeUrlGetter"]},{"name":"public class Builder","description":"io.spine.js.generate.output.snippet.MapExportSnippet.Builder","location":"proto-js-plugin/io.spine.js.generate.output.snippet/-map-export-snippet/-builder/index.html","searchKeys":["Builder","public class Builder","io.spine.js.generate.output.snippet.MapExportSnippet.Builder"]},{"name":"public class Builder","description":"io.spine.js.generate.output.snippet.Method.Builder","location":"proto-js-plugin/io.spine.js.generate.output.snippet/-method/-builder/index.html","searchKeys":["Builder","public class Builder","io.spine.js.generate.output.snippet.Method.Builder"]},{"name":"public class Comment extends CodeLine","description":"io.spine.js.generate.output.snippet.Comment","location":"proto-js-plugin/io.spine.js.generate.output.snippet/-comment/index.html","searchKeys":["Comment","public class Comment extends CodeLine","io.spine.js.generate.output.snippet.Comment"]},{"name":"public class Extension","description":"io.spine.js.gradle.Extension","location":"proto-js-plugin/io.spine.js.gradle/-extension/index.html","searchKeys":["Extension","public class Extension","io.spine.js.gradle.Extension"]},{"name":"public class Import extends CodeLine","description":"io.spine.js.generate.output.snippet.Import","location":"proto-js-plugin/io.spine.js.generate.output.snippet/-import/index.html","searchKeys":["Import","public class Import extends CodeLine","io.spine.js.generate.output.snippet.Import"]},{"name":"public class ImportStatement","description":"io.spine.js.generate.imports.ImportStatement","location":"proto-js-plugin/io.spine.js.generate.imports/-import-statement/index.html","searchKeys":["ImportStatement","public class ImportStatement","io.spine.js.generate.imports.ImportStatement"]},{"name":"public class MapExportSnippet implements Snippet","description":"io.spine.js.generate.output.snippet.MapExportSnippet","location":"proto-js-plugin/io.spine.js.generate.output.snippet/-map-export-snippet/index.html","searchKeys":["MapExportSnippet","public class MapExportSnippet implements Snippet","io.spine.js.generate.output.snippet.MapExportSnippet"]},{"name":"public class Method implements Snippet","description":"io.spine.js.generate.output.snippet.Method","location":"proto-js-plugin/io.spine.js.generate.output.snippet/-method/index.html","searchKeys":["Method","public class Method implements Snippet","io.spine.js.generate.output.snippet.Method"]},{"name":"public class ProtoJsPlugin","description":"io.spine.js.gradle.ProtoJsPlugin","location":"proto-js-plugin/io.spine.js.gradle/-proto-js-plugin/index.html","searchKeys":["ProtoJsPlugin","public class ProtoJsPlugin","io.spine.js.gradle.ProtoJsPlugin"]},{"name":"public class Return extends CodeLine","description":"io.spine.js.generate.output.snippet.Return","location":"proto-js-plugin/io.spine.js.generate.output.snippet/-return/index.html","searchKeys":["Return","public class Return extends CodeLine","io.spine.js.generate.output.snippet.Return"]},{"name":"public class VariableDeclaration extends CodeLine","description":"io.spine.js.generate.output.snippet.VariableDeclaration","location":"proto-js-plugin/io.spine.js.generate.output.snippet/-variable-declaration/index.html","searchKeys":["VariableDeclaration","public class VariableDeclaration extends CodeLine","io.spine.js.generate.output.snippet.VariableDeclaration"]},{"name":"public final class CodeLines","description":"io.spine.js.generate.output.CodeLines","location":"proto-js-plugin/io.spine.js.generate.output/-code-lines/index.html","searchKeys":["CodeLines","public final class CodeLines","io.spine.js.generate.output.CodeLines"]},{"name":"public final class FieldGenerators","description":"io.spine.js.generate.field.FieldGenerators","location":"proto-js-plugin/io.spine.js.generate.field/-field-generators/index.html","searchKeys":["FieldGenerators","public final class FieldGenerators","io.spine.js.generate.field.FieldGenerators"]},{"name":"public final class FieldPreconditions","description":"io.spine.js.generate.field.precondition.FieldPreconditions","location":"proto-js-plugin/io.spine.js.generate.field.precondition/-field-preconditions/index.html","searchKeys":["FieldPreconditions","public final class FieldPreconditions","io.spine.js.generate.field.precondition.FieldPreconditions"]},{"name":"public final class FieldToParse","description":"io.spine.js.generate.field.FieldToParse","location":"proto-js-plugin/io.spine.js.generate.field/-field-to-parse/index.html","searchKeys":["FieldToParse","public final class FieldToParse","io.spine.js.generate.field.FieldToParse"]},{"name":"public final class FileWriter","description":"io.spine.js.generate.output.FileWriter","location":"proto-js-plugin/io.spine.js.generate.output/-file-writer/index.html","searchKeys":["FileWriter","public final class FileWriter","io.spine.js.generate.output.FileWriter"]},{"name":"public final class GenerateIndexFile extends GenerationTask","description":"io.spine.js.generate.index.GenerateIndexFile","location":"proto-js-plugin/io.spine.js.generate.index/-generate-index-file/index.html","searchKeys":["GenerateIndexFile","public final class GenerateIndexFile extends GenerationTask","io.spine.js.generate.index.GenerateIndexFile"]},{"name":"public final class GenerateKnownTypeParsers extends GenerationTask","description":"io.spine.js.generate.parse.GenerateKnownTypeParsers","location":"proto-js-plugin/io.spine.js.generate.parse/-generate-known-type-parsers/index.html","searchKeys":["GenerateKnownTypeParsers","public final class GenerateKnownTypeParsers extends GenerationTask","io.spine.js.generate.parse.GenerateKnownTypeParsers"]},{"name":"public final class GeneratedParser implements Snippet","description":"io.spine.js.generate.parse.GeneratedParser","location":"proto-js-plugin/io.spine.js.generate.parse/-generated-parser/index.html","searchKeys":["GeneratedParser","public final class GeneratedParser implements Snippet","io.spine.js.generate.parse.GeneratedParser"]},{"name":"public final class JsFile","description":"io.spine.js.generate.imports.JsFile","location":"proto-js-plugin/io.spine.js.generate.imports/-js-file/index.html","searchKeys":["JsFile","public final class JsFile","io.spine.js.generate.imports.JsFile"]},{"name":"public final class JsProtocConfigurationPlugin","description":"io.spine.js.gradle.JsProtocConfigurationPlugin","location":"proto-js-plugin/io.spine.js.gradle/-js-protoc-configuration-plugin/index.html","searchKeys":["JsProtocConfigurationPlugin","public final class JsProtocConfigurationPlugin","io.spine.js.gradle.JsProtocConfigurationPlugin"]},{"name":"public final class PrimitiveParsers","description":"io.spine.js.generate.field.parser.primitive.PrimitiveParsers","location":"proto-js-plugin/io.spine.js.generate.field.parser.primitive/-primitive-parsers/index.html","searchKeys":["PrimitiveParsers","public final class PrimitiveParsers","io.spine.js.generate.field.parser.primitive.PrimitiveParsers"]},{"name":"public final class ResolveImports extends GenerationTask","description":"io.spine.js.generate.imports.ResolveImports","location":"proto-js-plugin/io.spine.js.generate.imports/-resolve-imports/index.html","searchKeys":["ResolveImports","public final class ResolveImports extends GenerationTask","io.spine.js.generate.imports.ResolveImports"]},{"name":"public final void performFor(FileSet fileSet)","description":"io.spine.js.generate.GenerationTask.performFor","location":"proto-js-plugin/io.spine.js.generate/-generation-task/perform-for.html","searchKeys":["performFor","public final void performFor(FileSet fileSet)","io.spine.js.generate.GenerationTask.performFor"]},{"name":"public interface Builder<B extends PrimitiveParser.Builder<B>>","description":"io.spine.js.generate.field.parser.primitive.PrimitiveParser.Builder","location":"proto-js-plugin/io.spine.js.generate.field.parser.primitive/-primitive-parser/-builder/index.html","searchKeys":["Builder","public interface Builder<B extends PrimitiveParser.Builder<B>>","io.spine.js.generate.field.parser.primitive.PrimitiveParser.Builder"]},{"name":"public interface FieldParser","description":"io.spine.js.generate.field.parser.FieldParser","location":"proto-js-plugin/io.spine.js.generate.field.parser/-field-parser/index.html","searchKeys":["FieldParser","public interface FieldParser","io.spine.js.generate.field.parser.FieldParser"]},{"name":"public interface FieldPrecondition","description":"io.spine.js.generate.field.precondition.FieldPrecondition","location":"proto-js-plugin/io.spine.js.generate.field.precondition/-field-precondition/index.html","searchKeys":["FieldPrecondition","public interface FieldPrecondition","io.spine.js.generate.field.precondition.FieldPrecondition"]},{"name":"public interface PrimitiveParser","description":"io.spine.js.generate.field.parser.primitive.PrimitiveParser","location":"proto-js-plugin/io.spine.js.generate.field.parser.primitive/-primitive-parser/index.html","searchKeys":["PrimitiveParser","public interface PrimitiveParser","io.spine.js.generate.field.parser.primitive.PrimitiveParser"]},{"name":"public interface ProcessImport implements UnaryOperator<T>","description":"io.spine.js.generate.imports.JsFile.ProcessImport","location":"proto-js-plugin/io.spine.js.generate.imports/-js-file/-process-import/index.html","searchKeys":["ProcessImport","public interface ProcessImport implements UnaryOperator<T>","io.spine.js.generate.imports.JsFile.ProcessImport"]},{"name":"public interface Snippet","description":"io.spine.js.generate.Snippet","location":"proto-js-plugin/io.spine.js.generate/-snippet/index.html","searchKeys":["Snippet","public interface Snippet","io.spine.js.generate.Snippet"]},{"name":"public int hashCode()","description":"io.spine.js.generate.output.CodeLine.hashCode","location":"proto-js-plugin/io.spine.js.generate.output/-code-line/hash-code.html","searchKeys":["hashCode","public int hashCode()","io.spine.js.generate.output.CodeLine.hashCode"]},{"name":"public int hashCode()","description":"io.spine.js.generate.output.CodeLines.hashCode","location":"proto-js-plugin/io.spine.js.generate.output/-code-lines/hash-code.html","searchKeys":["hashCode","public int hashCode()","io.spine.js.generate.output.CodeLines.hashCode"]},{"name":"public static CodeLines commaSeparated(List<CodeLine> lines)","description":"io.spine.js.generate.output.CodeLines.commaSeparated","location":"proto-js-plugin/io.spine.js.generate.output/-code-lines/comma-separated.html","searchKeys":["commaSeparated","public static CodeLines commaSeparated(List<CodeLine> lines)","io.spine.js.generate.output.CodeLines.commaSeparated"]},{"name":"public static CodeLine emptyLine()","description":"io.spine.js.generate.output.CodeLine.emptyLine","location":"proto-js-plugin/io.spine.js.generate.output/-code-line/empty-line.html","searchKeys":["emptyLine","public static CodeLine emptyLine()","io.spine.js.generate.output.CodeLine.emptyLine"]},{"name":"public static CodeLine of(String content)","description":"io.spine.js.generate.output.CodeLine.of","location":"proto-js-plugin/io.spine.js.generate.output/-code-line/of.html","searchKeys":["of","public static CodeLine of(String content)","io.spine.js.generate.output.CodeLine.of"]},{"name":"public static Comment generatedBySpine()","description":"io.spine.js.generate.output.snippet.Comment.generatedBySpine","location":"proto-js-plugin/io.spine.js.generate.output.snippet/-comment/generated-by-spine.html","searchKeys":["generatedBySpine","public static Comment generatedBySpine()","io.spine.js.generate.output.snippet.Comment.generatedBySpine"]},{"name":"public static Comment of(String text)","description":"io.spine.js.generate.output.snippet.Comment.of","location":"proto-js-plugin/io.spine.js.generate.output.snippet/-comment/of.html","searchKeys":["of","public static Comment of(String text)","io.spine.js.generate.output.snippet.Comment.of"]},{"name":"public static Directory getMainGenProto(Project project)","description":"io.spine.js.gradle.Extension.getMainGenProto","location":"proto-js-plugin/io.spine.js.gradle/-extension/get-main-gen-proto.html","searchKeys":["getMainGenProto","public static Directory getMainGenProto(Project project)","io.spine.js.gradle.Extension.getMainGenProto"]},{"name":"public static Directory getTestGenProtoDir(Project project)","description":"io.spine.js.gradle.Extension.getTestGenProtoDir","location":"proto-js-plugin/io.spine.js.gradle/-extension/get-test-gen-proto-dir.html","searchKeys":["getTestGenProtoDir","public static Directory getTestGenProtoDir(Project project)","io.spine.js.gradle.Extension.getTestGenProtoDir"]},{"name":"public static FieldGenerator createFor(FieldToParse field, CodeLines jsOutput)","description":"io.spine.js.generate.field.FieldGenerators.createFor","location":"proto-js-plugin/io.spine.js.generate.field/-field-generators/create-for.html","searchKeys":["createFor","public static FieldGenerator createFor(FieldToParse field, CodeLines jsOutput)","io.spine.js.generate.field.FieldGenerators.createFor"]},{"name":"public static FieldParser parserFor(FieldDescriptor field, CodeLines jsOutput)","description":"io.spine.js.generate.field.parser.FieldParser.parserFor","location":"proto-js-plugin/io.spine.js.generate.field.parser/-field-parser/parser-for.html","searchKeys":["parserFor","public static FieldParser parserFor(FieldDescriptor field, CodeLines jsOutput)","io.spine.js.generate.field.parser.FieldParser.parserFor"]},{"name":"public static FieldPrecondition preconditionFor(FieldDescriptor field, CodeLines jsOutput)","description":"io.spine.js.generate.field.precondition.FieldPreconditions.preconditionFor","location":"proto-js-plugin/io.spine.js.generate.field.precondition/-field-preconditions/precondition-for.html","searchKeys":["preconditionFor","public static FieldPrecondition preconditionFor(FieldDescriptor field, CodeLines jsOutput)","io.spine.js.generate.field.precondition.FieldPreconditions.preconditionFor"]},{"name":"public static FileWriter createFor(Directory directory, FileDescriptor file)","description":"io.spine.js.generate.output.FileWriter.createFor","location":"proto-js-plugin/io.spine.js.generate.output/-file-writer/create-for.html","searchKeys":["createFor","public static FileWriter createFor(Directory directory, FileDescriptor file)","io.spine.js.generate.output.FileWriter.createFor"]},{"name":"public static FileWriter createFor(Directory directory, LibraryFile libraryFile)","description":"io.spine.js.generate.output.FileWriter.createFor","location":"proto-js-plugin/io.spine.js.generate.output/-file-writer/create-for.html","searchKeys":["createFor","public static FileWriter createFor(Directory directory, LibraryFile libraryFile)","io.spine.js.generate.output.FileWriter.createFor"]},{"name":"public static File getMainDescriptorSet(Project project)","description":"io.spine.js.gradle.Extension.getMainDescriptorSet","location":"proto-js-plugin/io.spine.js.gradle/-extension/get-main-descriptor-set.html","searchKeys":["getMainDescriptorSet","public static File getMainDescriptorSet(Project project)","io.spine.js.gradle.Extension.getMainDescriptorSet"]},{"name":"public static File getTestDescriptorSet(Project project)","description":"io.spine.js.gradle.Extension.getTestDescriptorSet","location":"proto-js-plugin/io.spine.js.gradle/-extension/get-test-descriptor-set.html","searchKeys":["getTestDescriptorSet","public static File getTestDescriptorSet(Project project)","io.spine.js.gradle.Extension.getTestDescriptorSet"]},{"name":"public static GenerateKnownTypeParsers createFor(Directory generatedRoot)","description":"io.spine.js.generate.parse.GenerateKnownTypeParsers.createFor","location":"proto-js-plugin/io.spine.js.generate.parse/-generate-known-type-parsers/create-for.html","searchKeys":["createFor","public static GenerateKnownTypeParsers createFor(Directory generatedRoot)","io.spine.js.generate.parse.GenerateKnownTypeParsers.createFor"]},{"name":"public static ImmutableCollection<MessageType> targetTypes(FileDescriptor file)","description":"io.spine.js.generate.parse.GenerateKnownTypeParsers.targetTypes","location":"proto-js-plugin/io.spine.js.generate.parse/-generate-known-type-parsers/target-types.html","searchKeys":["targetTypes","public static ImmutableCollection<MessageType> targetTypes(FileDescriptor file)","io.spine.js.generate.parse.GenerateKnownTypeParsers.targetTypes"]},{"name":"public static Import fileRelativeTo(FileName fileToImport, FileName relativeTo)","description":"io.spine.js.generate.output.snippet.Import.fileRelativeTo","location":"proto-js-plugin/io.spine.js.generate.output.snippet/-import/file-relative-to.html","searchKeys":["fileRelativeTo","public static Import fileRelativeTo(FileName fileToImport, FileName relativeTo)","io.spine.js.generate.output.snippet.Import.fileRelativeTo"]},{"name":"public static Import fileRelativeToRoot(FileName file)","description":"io.spine.js.generate.output.snippet.Import.fileRelativeToRoot","location":"proto-js-plugin/io.spine.js.generate.output.snippet/-import/file-relative-to-root.html","searchKeys":["fileRelativeToRoot","public static Import fileRelativeToRoot(FileName file)","io.spine.js.generate.output.snippet.Import.fileRelativeToRoot"]},{"name":"public static Import library(String libraryName)","description":"io.spine.js.generate.output.snippet.Import.library","location":"proto-js-plugin/io.spine.js.generate.output.snippet/-import/library.html","searchKeys":["library","public static Import library(String libraryName)","io.spine.js.generate.output.snippet.Import.library"]},{"name":"public static List<ExternalModule> modules(Project project)","description":"io.spine.js.gradle.Extension.modules","location":"proto-js-plugin/io.spine.js.gradle/-extension/modules.html","searchKeys":["modules","public static List<ExternalModule> modules(Project project)","io.spine.js.gradle.Extension.modules"]},{"name":"public static MapExportSnippet.Builder newBuilder(String mapName)","description":"io.spine.js.generate.output.snippet.MapExportSnippet.newBuilder","location":"proto-js-plugin/io.spine.js.generate.output.snippet/-map-export-snippet/new-builder.html","searchKeys":["newBuilder","public static MapExportSnippet.Builder newBuilder(String mapName)","io.spine.js.generate.output.snippet.MapExportSnippet.newBuilder"]},{"name":"public static Method.Builder newBuilder(MethodReference methodReference)","description":"io.spine.js.generate.output.snippet.Method.newBuilder","location":"proto-js-plugin/io.spine.js.generate.output.snippet/-method/new-builder.html","searchKeys":["newBuilder","public static Method.Builder newBuilder(MethodReference methodReference)","io.spine.js.generate.output.snippet.Method.newBuilder"]},{"name":"public static PrimitiveParser createFor(Type fieldType, CodeLines jsOutput)","description":"io.spine.js.generate.field.parser.primitive.PrimitiveParsers.createFor","location":"proto-js-plugin/io.spine.js.generate.field.parser.primitive/-primitive-parsers/create-for.html","searchKeys":["createFor","public static PrimitiveParser createFor(Type fieldType, CodeLines jsOutput)","io.spine.js.generate.field.parser.primitive.PrimitiveParsers.createFor"]},{"name":"public static Return nullReference()","description":"io.spine.js.generate.output.snippet.Return.nullReference","location":"proto-js-plugin/io.spine.js.generate.output.snippet/-return/null-reference.html","searchKeys":["nullReference","public static Return nullReference()","io.spine.js.generate.output.snippet.Return.nullReference"]},{"name":"public static Return stringLiteral(String literal)","description":"io.spine.js.generate.output.snippet.Return.stringLiteral","location":"proto-js-plugin/io.spine.js.generate.output.snippet/-return/string-literal.html","searchKeys":["stringLiteral","public static Return stringLiteral(String literal)","io.spine.js.generate.output.snippet.Return.stringLiteral"]},{"name":"public static Return value(Object value)","description":"io.spine.js.generate.output.snippet.Return.value","location":"proto-js-plugin/io.spine.js.generate.output.snippet/-return/value.html","searchKeys":["value","public static Return value(Object value)","io.spine.js.generate.output.snippet.Return.value"]},{"name":"public static String parseMethodCall(String parserVariable, String valueToParse)","description":"io.spine.js.generate.parse.GeneratedParser.parseMethodCall","location":"proto-js-plugin/io.spine.js.generate.parse/-generated-parser/parse-method-call.html","searchKeys":["parseMethodCall","public static String parseMethodCall(String parserVariable, String valueToParse)","io.spine.js.generate.parse.GeneratedParser.parseMethodCall"]},{"name":"public static VariableDeclaration initialized(String name, String value)","description":"io.spine.js.generate.output.snippet.VariableDeclaration.initialized","location":"proto-js-plugin/io.spine.js.generate.output.snippet/-variable-declaration/initialized.html","searchKeys":["initialized","public static VariableDeclaration initialized(String name, String value)","io.spine.js.generate.output.snippet.VariableDeclaration.initialized"]},{"name":"public static VariableDeclaration newInstance(String name, TypeName type)","description":"io.spine.js.generate.output.snippet.VariableDeclaration.newInstance","location":"proto-js-plugin/io.spine.js.generate.output.snippet/-variable-declaration/new-instance.html","searchKeys":["newInstance","public static VariableDeclaration newInstance(String name, TypeName type)","io.spine.js.generate.output.snippet.VariableDeclaration.newInstance"]},{"name":"public void AppendTypeUrlGetter(Directory generatedRoot)","description":"io.spine.js.generate.AppendTypeUrlGetter.AppendTypeUrlGetter","location":"proto-js-plugin/io.spine.js.generate/-append-type-url-getter/-append-type-url-getter.html","searchKeys":["AppendTypeUrlGetter","public void AppendTypeUrlGetter(Directory generatedRoot)","io.spine.js.generate.AppendTypeUrlGetter.AppendTypeUrlGetter"]},{"name":"public void CodeLine()","description":"io.spine.js.generate.output.CodeLine.CodeLine","location":"proto-js-plugin/io.spine.js.generate.output/-code-line/-code-line.html","searchKeys":["CodeLine","public void CodeLine()","io.spine.js.generate.output.CodeLine.CodeLine"]},{"name":"public void CodeLines()","description":"io.spine.js.generate.output.CodeLines.CodeLines","location":"proto-js-plugin/io.spine.js.generate.output/-code-lines/-code-lines.html","searchKeys":["CodeLines","public void CodeLines()","io.spine.js.generate.output.CodeLines.CodeLines"]},{"name":"public void CodeLines(Indent indentation)","description":"io.spine.js.generate.output.CodeLines.CodeLines","location":"proto-js-plugin/io.spine.js.generate.output/-code-lines/-code-lines.html","searchKeys":["CodeLines","public void CodeLines(Indent indentation)","io.spine.js.generate.output.CodeLines.CodeLines"]},{"name":"public void Extension()","description":"io.spine.js.gradle.Extension.Extension","location":"proto-js-plugin/io.spine.js.gradle/-extension/-extension.html","searchKeys":["Extension","public void Extension()","io.spine.js.gradle.Extension.Extension"]},{"name":"public void FieldToParse(FieldDescriptor descriptor, String objectVariable, String messageVariable)","description":"io.spine.js.generate.field.FieldToParse.FieldToParse","location":"proto-js-plugin/io.spine.js.generate.field/-field-to-parse/-field-to-parse.html","searchKeys":["FieldToParse","public void FieldToParse(FieldDescriptor descriptor, String objectVariable, String messageVariable)","io.spine.js.generate.field.FieldToParse.FieldToParse"]},{"name":"public void GenerateIndexFile(Directory generatedRoot)","description":"io.spine.js.generate.index.GenerateIndexFile.GenerateIndexFile","location":"proto-js-plugin/io.spine.js.generate.index/-generate-index-file/-generate-index-file.html","searchKeys":["GenerateIndexFile","public void GenerateIndexFile(Directory generatedRoot)","io.spine.js.generate.index.GenerateIndexFile.GenerateIndexFile"]},{"name":"public void ImportStatement(String text, File originFile)","description":"io.spine.js.generate.imports.ImportStatement.ImportStatement","location":"proto-js-plugin/io.spine.js.generate.imports/-import-statement/-import-statement.html","searchKeys":["ImportStatement","public void ImportStatement(String text, File originFile)","io.spine.js.generate.imports.ImportStatement.ImportStatement"]},{"name":"public void JsFile(Path path)","description":"io.spine.js.generate.imports.JsFile.JsFile","location":"proto-js-plugin/io.spine.js.generate.imports/-js-file/-js-file.html","searchKeys":["JsFile","public void JsFile(Path path)","io.spine.js.generate.imports.JsFile.JsFile"]},{"name":"public void JsProtocConfigurationPlugin()","description":"io.spine.js.gradle.JsProtocConfigurationPlugin.JsProtocConfigurationPlugin","location":"proto-js-plugin/io.spine.js.gradle/-js-protoc-configuration-plugin/-js-protoc-configuration-plugin.html","searchKeys":["JsProtocConfigurationPlugin","public void JsProtocConfigurationPlugin()","io.spine.js.gradle.JsProtocConfigurationPlugin.JsProtocConfigurationPlugin"]},{"name":"public void ProtoJsPlugin()","description":"io.spine.js.gradle.ProtoJsPlugin.ProtoJsPlugin","location":"proto-js-plugin/io.spine.js.gradle/-proto-js-plugin/-proto-js-plugin.html","searchKeys":["ProtoJsPlugin","public void ProtoJsPlugin()","io.spine.js.gradle.ProtoJsPlugin.ProtoJsPlugin"]},{"name":"public void ResolveImports(Directory generatedRoot, Collection<ExternalModule> modules)","description":"io.spine.js.generate.imports.ResolveImports.ResolveImports","location":"proto-js-plugin/io.spine.js.generate.imports/-resolve-imports/-resolve-imports.html","searchKeys":["ResolveImports","public void ResolveImports(Directory generatedRoot, Collection<ExternalModule> modules)","io.spine.js.generate.imports.ResolveImports.ResolveImports"]},{"name":"public void append(CodeLines appended)","description":"io.spine.js.generate.output.CodeLines.append","location":"proto-js-plugin/io.spine.js.generate.output/-code-lines/append.html","searchKeys":["append","public void append(CodeLines appended)","io.spine.js.generate.output.CodeLines.append"]},{"name":"public void append(CodeLines jsOutput)","description":"io.spine.js.generate.output.FileWriter.append","location":"proto-js-plugin/io.spine.js.generate.output/-file-writer/append.html","searchKeys":["append","public void append(CodeLines jsOutput)","io.spine.js.generate.output.FileWriter.append"]},{"name":"public void append(CodeLine line)","description":"io.spine.js.generate.output.CodeLines.append","location":"proto-js-plugin/io.spine.js.generate.output/-code-lines/append.html","searchKeys":["append","public void append(CodeLine line)","io.spine.js.generate.output.CodeLines.append"]},{"name":"public void append(Snippet snippet)","description":"io.spine.js.generate.output.CodeLines.append","location":"proto-js-plugin/io.spine.js.generate.output/-code-lines/append.html","searchKeys":["append","public void append(Snippet snippet)","io.spine.js.generate.output.CodeLines.append"]},{"name":"public void append(String codeLine)","description":"io.spine.js.generate.output.CodeLines.append","location":"proto-js-plugin/io.spine.js.generate.output/-code-lines/append.html","searchKeys":["append","public void append(String codeLine)","io.spine.js.generate.output.CodeLines.append"]},{"name":"public void apply(Project project)","description":"io.spine.js.gradle.ProtoJsPlugin.apply","location":"proto-js-plugin/io.spine.js.gradle/-proto-js-plugin/apply.html","searchKeys":["apply","public void apply(Project project)","io.spine.js.gradle.ProtoJsPlugin.apply"]},{"name":"public void decreaseDepth()","description":"io.spine.js.generate.output.CodeLines.decreaseDepth","location":"proto-js-plugin/io.spine.js.generate.output/-code-lines/decrease-depth.html","searchKeys":["decreaseDepth","public void decreaseDepth()","io.spine.js.generate.output.CodeLines.decreaseDepth"]},{"name":"public void enterBlock(String blockHeader)","description":"io.spine.js.generate.output.CodeLines.enterBlock","location":"proto-js-plugin/io.spine.js.generate.output/-code-lines/enter-block.html","searchKeys":["enterBlock","public void enterBlock(String blockHeader)","io.spine.js.generate.output.CodeLines.enterBlock"]},{"name":"public void enterElseBlock()","description":"io.spine.js.generate.output.CodeLines.enterElseBlock","location":"proto-js-plugin/io.spine.js.generate.output/-code-lines/enter-else-block.html","searchKeys":["enterElseBlock","public void enterElseBlock()","io.spine.js.generate.output.CodeLines.enterElseBlock"]},{"name":"public void enterIfBlock(String condition)","description":"io.spine.js.generate.output.CodeLines.enterIfBlock","location":"proto-js-plugin/io.spine.js.generate.output/-code-lines/enter-if-block.html","searchKeys":["enterIfBlock","public void enterIfBlock(String condition)","io.spine.js.generate.output.CodeLines.enterIfBlock"]},{"name":"public void enterMethod(String methodName, Array<String> methodArgs)","description":"io.spine.js.generate.output.CodeLines.enterMethod","location":"proto-js-plugin/io.spine.js.generate.output/-code-lines/enter-method.html","searchKeys":["enterMethod","public void enterMethod(String methodName, Array<String> methodArgs)","io.spine.js.generate.output.CodeLines.enterMethod"]},{"name":"public void exitBlock()","description":"io.spine.js.generate.output.CodeLines.exitBlock","location":"proto-js-plugin/io.spine.js.generate.output/-code-lines/exit-block.html","searchKeys":["exitBlock","public void exitBlock()","io.spine.js.generate.output.CodeLines.exitBlock"]},{"name":"public void exitMethod()","description":"io.spine.js.generate.output.CodeLines.exitMethod","location":"proto-js-plugin/io.spine.js.generate.output/-code-lines/exit-method.html","searchKeys":["exitMethod","public void exitMethod()","io.spine.js.generate.output.CodeLines.exitMethod"]},{"name":"public void ifNotNull(String value)","description":"io.spine.js.generate.output.CodeLines.ifNotNull","location":"proto-js-plugin/io.spine.js.generate.output/-code-lines/if-not-null.html","searchKeys":["ifNotNull","public void ifNotNull(String value)","io.spine.js.generate.output.CodeLines.ifNotNull"]},{"name":"public void ifNotNullOrUndefined(String value)","description":"io.spine.js.generate.output.CodeLines.ifNotNullOrUndefined","location":"proto-js-plugin/io.spine.js.generate.output/-code-lines/if-not-null-or-undefined.html","searchKeys":["ifNotNullOrUndefined","public void ifNotNullOrUndefined(String value)","io.spine.js.generate.output.CodeLines.ifNotNullOrUndefined"]},{"name":"public void ifNotUndefined(String value)","description":"io.spine.js.generate.output.CodeLines.ifNotUndefined","location":"proto-js-plugin/io.spine.js.generate.output/-code-lines/if-not-undefined.html","searchKeys":["ifNotUndefined","public void ifNotUndefined(String value)","io.spine.js.generate.output.CodeLines.ifNotUndefined"]},{"name":"public void ifNull(String value)","description":"io.spine.js.generate.output.CodeLines.ifNull","location":"proto-js-plugin/io.spine.js.generate.output/-code-lines/if-null.html","searchKeys":["ifNull","public void ifNull(String value)","io.spine.js.generate.output.CodeLines.ifNull"]},{"name":"public void increaseDepth()","description":"io.spine.js.generate.output.CodeLines.increaseDepth","location":"proto-js-plugin/io.spine.js.generate.output/-code-lines/increase-depth.html","searchKeys":["increaseDepth","public void increaseDepth()","io.spine.js.generate.output.CodeLines.increaseDepth"]},{"name":"public void processImports(Predicate<ImportStatement> importFilter, JsFile.ProcessImport processFunction)","description":"io.spine.js.generate.imports.JsFile.processImports","location":"proto-js-plugin/io.spine.js.generate.imports/-js-file/process-imports.html","searchKeys":["processImports","public void processImports(Predicate<ImportStatement> importFilter, JsFile.ProcessImport processFunction)","io.spine.js.generate.imports.JsFile.processImports"]},{"name":"public void write(CodeLines jsOutput)","description":"io.spine.js.generate.output.FileWriter.write","location":"proto-js-plugin/io.spine.js.generate.output/-file-writer/write.html","searchKeys":["write","public void write(CodeLines jsOutput)","io.spine.js.generate.output.FileWriter.write"]}]
